{"id":"decomp-ambig-cc-01","fixtureClass":"AMBIGUOUS","expectedClass":"CODE-CHANGE","epicPlanExcerpt":"Sub-Task Decomposition:\n- Improve decomposer prompt clarity for multi-file epic edge cases\n- Test with sample epics","subtaskHint":"Improve decomposer prompt clarity for multi-file epic edge cases","ground_truth_rationale":"Decomposer prompt lives in SKILL.md → modifying it is CODE-CHANGE per explicit rule","tricky_aspect":"'improve prompt' sounds like documentation but prompt lives in SKILL.md which triggers CODE-CHANGE"}
